{
  "project_info": {
    "project_number": "175970429089",
    "project_id": "mycrypto-ec750",
    "storage_bucket": "mycrypto-ec750.firebasestorage.app"
  },
  "client": [
    {
      "client_info": {
        "mobilesdk_app_id": "1:175970429089:android:38aadd11f46fbc57af28e0",
        "android_client_info": {
          "package_name": "com.mycrypto"
        }
      },
      "oauth_client": [],
      "api_key": [
        {
          "current_key": "AIzaSyCLEiv0uQLeOn2wJrDCMYGjLhkqwEemPzc"
        }
      ],
      "services": {
        "appinvite_service": {
          "other_platform_oauth_client": []
        }
      }
    }
  ],
  "configuration_version": "1"
}